<annotation>
	<folder>Audubon2022</folder>
	<filename>DJI_20210520121512_0748</filename>
	<source>
		<database>The Audubon2022 Database</database>
		<annotation>Audubon2022 Spring</annotation>
		<image>None</image>
	</source>
	<size>
		<width>231</width>
		<height>321</height>
		<depth>3</depth>
	</size>
	<segmented>0</segmented>
	<object>
		<name>BCNHA</name>
		<pose>0</pose>
		<truncated>1</truncated>
		<difficult>2</difficult>
		<bndbox>
			<xmin>5576</xmin>
			<ymin>5268</ymin>
			<xmax>5658</xmax>
			<ymax>5323</ymax>
		</bndbox>
	</object>
	<object>
		<name>LAGUA</name>
		<pose>0</pose>
		<truncated>1</truncated>
		<difficult>2</difficult>
		<bndbox>
			<xmin>1004</xmin>
			<ymin>1484</ymin>
			<xmax>1092</xmax>
			<ymax>1526</ymax>
		</bndbox>
	</object>
	<object>
		<name>LAGUA</name>
		<pose>0</pose>
		<truncated>1</truncated>
		<difficult>2</difficult>
		<bndbox>
			<xmin>1054</xmin>
			<ymin>2036</ymin>
			<xmax>1118</xmax>
			<ymax>2118</ymax>
		</bndbox>
	</object>
	<object>
		<name>LAGUA</name>
		<pose>0</pose>
		<truncated>1</truncated>
		<difficult>2</difficult>
		<bndbox>
			<xmin>2392</xmin>
			<ymin>2155</ymin>
			<xmax>2459</xmax>
			<ymax>2240</ymax>
		</bndbox>
	</object>
	<object>
		<name>LAGUA</name>
		<pose>0</pose>
		<truncated>1</truncated>
		<difficult>2</difficult>
		<bndbox>
			<xmin>2178</xmin>
			<ymin>2063</ymin>
			<xmax>2226</xmax>
			<ymax>2148</ymax>
		</bndbox>
	</object>
	<object>
		<name>LAGUA</name>
		<pose>0</pose>
		<truncated>1</truncated>
		<difficult>2</difficult>
		<bndbox>
			<xmin>386</xmin>
			<ymin>2608</ymin>
			<xmax>434</xmax>
			<ymax>2702</ymax>
		</bndbox>
	</object>
	<object>
		<name>LAGUA</name>
		<pose>0</pose>
		<truncated>1</truncated>
		<difficult>2</difficult>
		<bndbox>
			<xmin>414</xmin>
			<ymin>2646</ymin>
			<xmax>470</xmax>
			<ymax>2740</ymax>
		</bndbox>
	</object>
	<object>
		<name>LAGUA</name>
		<pose>0</pose>
		<truncated>1</truncated>
		<difficult>2</difficult>
		<bndbox>
			<xmin>1047</xmin>
			<ymin>4623</ymin>
			<xmax>1140</xmax>
			<ymax>4690</ymax>
		</bndbox>
	</object>
	<object>
		<name>LAGUA</name>
		<pose>0</pose>
		<truncated>1</truncated>
		<difficult>2</difficult>
		<bndbox>
			<xmin>394</xmin>
			<ymin>4720</ymin>
			<xmax>476</xmax>
			<ymax>4808</ymax>
		</bndbox>
	</object>
	<object>
		<name>LAGUA</name>
		<pose>0</pose>
		<truncated>1</truncated>
		<difficult>2</difficult>
		<bndbox>
			<xmin>1526</xmin>
			<ymin>4908</ymin>
			<xmax>1624</xmax>
			<ymax>4964</ymax>
		</bndbox>
	</object>
	<object>
		<name>LAGUA</name>
		<pose>0</pose>
		<truncated>1</truncated>
		<difficult>2</difficult>
		<bndbox>
			<xmin>2028</xmin>
			<ymin>5036</ymin>
			<xmax>2102</xmax>
			<ymax>5090</ymax>
		</bndbox>
	</object>
	<object>
		<name>LAGUA</name>
		<pose>0</pose>
		<truncated>1</truncated>
		<difficult>2</difficult>
		<bndbox>
			<xmin>1795</xmin>
			<ymin>5334</ymin>
			<xmax>1866</xmax>
			<ymax>5407</ymax>
		</bndbox>
	</object>
	<object>
		<name>LAGUA</name>
		<pose>0</pose>
		<truncated>1</truncated>
		<difficult>2</difficult>
		<bndbox>
			<xmin>1370</xmin>
			<ymin>5028</ymin>
			<xmax>1455</xmax>
			<ymax>5100</ymax>
		</bndbox>
	</object>
	<object>
		<name>LAGUA</name>
		<pose>0</pose>
		<truncated>1</truncated>
		<difficult>2</difficult>
		<bndbox>
			<xmin>678</xmin>
			<ymin>5139</ymin>
			<xmax>756</xmax>
			<ymax>5230</ymax>
		</bndbox>
	</object>
	<object>
		<name>LAGUA</name>
		<pose>0</pose>
		<truncated>1</truncated>
		<difficult>2</difficult>
		<bndbox>
			<xmin>1435</xmin>
			<ymin>5418</ymin>
			<xmax>1516</xmax>
			<ymax>5460</ymax>
		</bndbox>
	</object>
	<object>
		<name>LAGUA</name>
		<pose>0</pose>
		<truncated>1</truncated>
		<difficult>2</difficult>
		<bndbox>
			<xmin>3006</xmin>
			<ymin>4770</ymin>
			<xmax>3075</xmax>
			<ymax>4840</ymax>
		</bndbox>
	</object>
	<object>
		<name>LAGUA</name>
		<pose>0</pose>
		<truncated>1</truncated>
		<difficult>2</difficult>
		<bndbox>
			<xmin>3568</xmin>
			<ymin>4732</ymin>
			<xmax>3659</xmax>
			<ymax>4790</ymax>
		</bndbox>
	</object>
	<object>
		<name>LAGUA</name>
		<pose>0</pose>
		<truncated>1</truncated>
		<difficult>2</difficult>
		<bndbox>
			<xmin>4408</xmin>
			<ymin>4762</ymin>
			<xmax>4492</xmax>
			<ymax>4812</ymax>
		</bndbox>
	</object>
	<object>
		<name>LAGUA</name>
		<pose>0</pose>
		<truncated>1</truncated>
		<difficult>2</difficult>
		<bndbox>
			<xmin>4210</xmin>
			<ymin>3998</ymin>
			<xmax>4314</xmax>
			<ymax>4044</ymax>
		</bndbox>
	</object>
	<object>
		<name>LAGUA</name>
		<pose>0</pose>
		<truncated>1</truncated>
		<difficult>2</difficult>
		<bndbox>
			<xmin>4266</xmin>
			<ymin>3887</ymin>
			<xmax>4362</xmax>
			<ymax>3944</ymax>
		</bndbox>
	</object>
	<object>
		<name>LAGUA</name>
		<pose>0</pose>
		<truncated>1</truncated>
		<difficult>2</difficult>
		<bndbox>
			<xmin>4255</xmin>
			<ymin>3751</ymin>
			<xmax>4344</xmax>
			<ymax>3804</ymax>
		</bndbox>
	</object>
	<object>
		<name>LAGUA</name>
		<pose>0</pose>
		<truncated>1</truncated>
		<difficult>2</difficult>
		<bndbox>
			<xmin>3819</xmin>
			<ymin>3855</ymin>
			<xmax>3918</xmax>
			<ymax>3916</ymax>
		</bndbox>
	</object>
	<object>
		<name>LAGUA</name>
		<pose>0</pose>
		<truncated>1</truncated>
		<difficult>2</difficult>
		<bndbox>
			<xmin>3114</xmin>
			<ymin>4019</ymin>
			<xmax>3182</xmax>
			<ymax>4112</ymax>
		</bndbox>
	</object>
	<object>
		<name>LAGUA</name>
		<pose>0</pose>
		<truncated>1</truncated>
		<difficult>2</difficult>
		<bndbox>
			<xmin>3848</xmin>
			<ymin>3479</ymin>
			<xmax>3940</xmax>
			<ymax>3532</ymax>
		</bndbox>
	</object>
	<object>
		<name>LAGUA</name>
		<pose>0</pose>
		<truncated>1</truncated>
		<difficult>2</difficult>
		<bndbox>
			<xmin>3904</xmin>
			<ymin>3358</ymin>
			<xmax>3956</xmax>
			<ymax>3435</ymax>
		</bndbox>
	</object>
	<object>
		<name>LAGUA</name>
		<pose>0</pose>
		<truncated>1</truncated>
		<difficult>2</difficult>
		<bndbox>
			<xmin>3192</xmin>
			<ymin>3558</ymin>
			<xmax>3288</xmax>
			<ymax>3608</ymax>
		</bndbox>
	</object>
	<object>
		<name>LAGUA</name>
		<pose>0</pose>
		<truncated>1</truncated>
		<difficult>2</difficult>
		<bndbox>
			<xmin>3323</xmin>
			<ymin>2638</ymin>
			<xmax>3390</xmax>
			<ymax>2719</ymax>
		</bndbox>
	</object>
	<object>
		<name>LAGUA</name>
		<pose>0</pose>
		<truncated>1</truncated>
		<difficult>2</difficult>
		<bndbox>
			<xmin>2891</xmin>
			<ymin>2634</ymin>
			<xmax>2958</xmax>
			<ymax>2686</ymax>
		</bndbox>
	</object>
	<object>
		<name>LAGUA</name>
		<pose>0</pose>
		<truncated>1</truncated>
		<difficult>2</difficult>
		<bndbox>
			<xmin>2651</xmin>
			<ymin>2080</ymin>
			<xmax>2704</xmax>
			<ymax>2170</ymax>
		</bndbox>
	</object>
	<object>
		<name>LAGUA</name>
		<pose>0</pose>
		<truncated>1</truncated>
		<difficult>2</difficult>
		<bndbox>
			<xmin>3484</xmin>
			<ymin>2072</ymin>
			<xmax>3532</xmax>
			<ymax>2155</ymax>
		</bndbox>
	</object>
	<object>
		<name>LAGUA</name>
		<pose>0</pose>
		<truncated>1</truncated>
		<difficult>2</difficult>
		<bndbox>
			<xmin>3575</xmin>
			<ymin>1411</ymin>
			<xmax>3627</xmax>
			<ymax>1488</ymax>
		</bndbox>
	</object>
	<object>
		<name>LAGUA</name>
		<pose>0</pose>
		<truncated>1</truncated>
		<difficult>2</difficult>
		<bndbox>
			<xmin>4330</xmin>
			<ymin>1292</ymin>
			<xmax>4402</xmax>
			<ymax>1374</ymax>
		</bndbox>
	</object>
	<object>
		<name>LAGUA</name>
		<pose>0</pose>
		<truncated>1</truncated>
		<difficult>2</difficult>
		<bndbox>
			<xmin>3504</xmin>
			<ymin>1216</ymin>
			<xmax>3568</xmax>
			<ymax>1315</ymax>
		</bndbox>
	</object>
	<object>
		<name>LAGUA</name>
		<pose>0</pose>
		<truncated>1</truncated>
		<difficult>2</difficult>
		<bndbox>
			<xmin>2975</xmin>
			<ymin>1232</ymin>
			<xmax>3015</xmax>
			<ymax>1326</ymax>
		</bndbox>
	</object>
	<object>
		<name>LAGUA</name>
		<pose>0</pose>
		<truncated>1</truncated>
		<difficult>2</difficult>
		<bndbox>
			<xmin>3776</xmin>
			<ymin>152</ymin>
			<xmax>3830</xmax>
			<ymax>234</ymax>
		</bndbox>
	</object>
	<object>
		<name>LAGUA</name>
		<pose>0</pose>
		<truncated>1</truncated>
		<difficult>2</difficult>
		<bndbox>
			<xmin>6344</xmin>
			<ymin>323</ymin>
			<xmax>6412</xmax>
			<ymax>403</ymax>
		</bndbox>
	</object>
	<object>
		<name>LAGUA</name>
		<pose>0</pose>
		<truncated>1</truncated>
		<difficult>2</difficult>
		<bndbox>
			<xmin>5896</xmin>
			<ymin>484</ymin>
			<xmax>5999</xmax>
			<ymax>543</ymax>
		</bndbox>
	</object>
	<object>
		<name>LAGUA</name>
		<pose>0</pose>
		<truncated>1</truncated>
		<difficult>2</difficult>
		<bndbox>
			<xmin>5334</xmin>
			<ymin>603</ymin>
			<xmax>5416</xmax>
			<ymax>686</ymax>
		</bndbox>
	</object>
	<object>
		<name>LAGUA</name>
		<pose>0</pose>
		<truncated>1</truncated>
		<difficult>2</difficult>
		<bndbox>
			<xmin>4818</xmin>
			<ymin>580</ymin>
			<xmax>4867</xmax>
			<ymax>672</ymax>
		</bndbox>
	</object>
	<object>
		<name>LAGUA</name>
		<pose>0</pose>
		<truncated>1</truncated>
		<difficult>2</difficult>
		<bndbox>
			<xmin>6163</xmin>
			<ymin>943</ymin>
			<xmax>6258</xmax>
			<ymax>1020</ymax>
		</bndbox>
	</object>
	<object>
		<name>LAGUA</name>
		<pose>0</pose>
		<truncated>1</truncated>
		<difficult>2</difficult>
		<bndbox>
			<xmin>6084</xmin>
			<ymin>1074</ymin>
			<xmax>6192</xmax>
			<ymax>1126</ymax>
		</bndbox>
	</object>
	<object>
		<name>LAGUA</name>
		<pose>0</pose>
		<truncated>1</truncated>
		<difficult>2</difficult>
		<bndbox>
			<xmin>6799</xmin>
			<ymin>887</ymin>
			<xmax>6863</xmax>
			<ymax>975</ymax>
		</bndbox>
	</object>
	<object>
		<name>LAGUA</name>
		<pose>0</pose>
		<truncated>1</truncated>
		<difficult>2</difficult>
		<bndbox>
			<xmin>6547</xmin>
			<ymin>1395</ymin>
			<xmax>6618</xmax>
			<ymax>1463</ymax>
		</bndbox>
	</object>
	<object>
		<name>LAGUA</name>
		<pose>0</pose>
		<truncated>1</truncated>
		<difficult>2</difficult>
		<bndbox>
			<xmin>6787</xmin>
			<ymin>1692</ymin>
			<xmax>6874</xmax>
			<ymax>1766</ymax>
		</bndbox>
	</object>
	<object>
		<name>LAGUA</name>
		<pose>0</pose>
		<truncated>1</truncated>
		<difficult>2</difficult>
		<bndbox>
			<xmin>5020</xmin>
			<ymin>1774</ymin>
			<xmax>5064</xmax>
			<ymax>1866</ymax>
		</bndbox>
	</object>
	<object>
		<name>LAGUA</name>
		<pose>0</pose>
		<truncated>1</truncated>
		<difficult>2</difficult>
		<bndbox>
			<xmin>6140</xmin>
			<ymin>2807</ymin>
			<xmax>6223</xmax>
			<ymax>2874</ymax>
		</bndbox>
	</object>
	<object>
		<name>LAGUA</name>
		<pose>0</pose>
		<truncated>1</truncated>
		<difficult>2</difficult>
		<bndbox>
			<xmin>6527</xmin>
			<ymin>3230</ymin>
			<xmax>6603</xmax>
			<ymax>3316</ymax>
		</bndbox>
	</object>
	<object>
		<name>LAGUA</name>
		<pose>0</pose>
		<truncated>1</truncated>
		<difficult>2</difficult>
		<bndbox>
			<xmin>5440</xmin>
			<ymin>3271</ymin>
			<xmax>5484</xmax>
			<ymax>3356</ymax>
		</bndbox>
	</object>
	<object>
		<name>LAGUA</name>
		<pose>0</pose>
		<truncated>1</truncated>
		<difficult>2</difficult>
		<bndbox>
			<xmin>5502</xmin>
			<ymin>3420</ymin>
			<xmax>5562</xmax>
			<ymax>3495</ymax>
		</bndbox>
	</object>
	<object>
		<name>LAGUA</name>
		<pose>0</pose>
		<truncated>1</truncated>
		<difficult>2</difficult>
		<bndbox>
			<xmin>6296</xmin>
			<ymin>3772</ymin>
			<xmax>6382</xmax>
			<ymax>3836</ymax>
		</bndbox>
	</object>
	<object>
		<name>LAGUA</name>
		<pose>0</pose>
		<truncated>1</truncated>
		<difficult>2</difficult>
		<bndbox>
			<xmin>5447</xmin>
			<ymin>4344</ymin>
			<xmax>5528</xmax>
			<ymax>4404</ymax>
		</bndbox>
	</object>
	<object>
		<name>LAGUA</name>
		<pose>0</pose>
		<truncated>1</truncated>
		<difficult>2</difficult>
		<bndbox>
			<xmin>6536</xmin>
			<ymin>4358</ymin>
			<xmax>6620</xmax>
			<ymax>4424</ymax>
		</bndbox>
	</object>
	<object>
		<name>LAGUA</name>
		<pose>0</pose>
		<truncated>1</truncated>
		<difficult>2</difficult>
		<bndbox>
			<xmin>5987</xmin>
			<ymin>4803</ymin>
			<xmax>6048</xmax>
			<ymax>4912</ymax>
		</bndbox>
	</object>
	<object>
		<name>LAGUA</name>
		<pose>0</pose>
		<truncated>1</truncated>
		<difficult>2</difficult>
		<bndbox>
			<xmin>5591</xmin>
			<ymin>4700</ymin>
			<xmax>5674</xmax>
			<ymax>4755</ymax>
		</bndbox>
	</object>
	<object>
		<name>LAGUA</name>
		<pose>0</pose>
		<truncated>1</truncated>
		<difficult>2</difficult>
		<bndbox>
			<xmin>6324</xmin>
			<ymin>4982</ymin>
			<xmax>6420</xmax>
			<ymax>5040</ymax>
		</bndbox>
	</object>
	<object>
		<name>LAGUA</name>
		<pose>0</pose>
		<truncated>1</truncated>
		<difficult>2</difficult>
		<bndbox>
			<xmin>4735</xmin>
			<ymin>4959</ymin>
			<xmax>4834</xmax>
			<ymax>5019</ymax>
		</bndbox>
	</object>
	<object>
		<name>LAGUA</name>
		<pose>0</pose>
		<truncated>1</truncated>
		<difficult>2</difficult>
		<bndbox>
			<xmin>5175</xmin>
			<ymin>5214</ymin>
			<xmax>5243</xmax>
			<ymax>5283</ymax>
		</bndbox>
	</object>
	<object>
		<name>LAGUA</name>
		<pose>0</pose>
		<truncated>1</truncated>
		<difficult>2</difficult>
		<bndbox>
			<xmin>7325</xmin>
			<ymin>5007</ymin>
			<xmax>7391</xmax>
			<ymax>5080</ymax>
		</bndbox>
	</object>
	<object>
		<name>LAGUA</name>
		<pose>0</pose>
		<truncated>1</truncated>
		<difficult>2</difficult>
		<bndbox>
			<xmin>8056</xmin>
			<ymin>4312</ymin>
			<xmax>8145</xmax>
			<ymax>4377</ymax>
		</bndbox>
	</object>
	<object>
		<name>LAGUA</name>
		<pose>0</pose>
		<truncated>1</truncated>
		<difficult>2</difficult>
		<bndbox>
			<xmin>7763</xmin>
			<ymin>3842</ymin>
			<xmax>7822</xmax>
			<ymax>3921</ymax>
		</bndbox>
	</object>
	<object>
		<name>LAGUA</name>
		<pose>0</pose>
		<truncated>1</truncated>
		<difficult>2</difficult>
		<bndbox>
			<xmin>7444</xmin>
			<ymin>3437</ymin>
			<xmax>7551</xmax>
			<ymax>3516</ymax>
		</bndbox>
	</object>
	<object>
		<name>LAGUA</name>
		<pose>0</pose>
		<truncated>1</truncated>
		<difficult>2</difficult>
		<bndbox>
			<xmin>7541</xmin>
			<ymin>2793</ymin>
			<xmax>7597</xmax>
			<ymax>2876</ymax>
		</bndbox>
	</object>
	<object>
		<name>LAGUA</name>
		<pose>0</pose>
		<truncated>1</truncated>
		<difficult>2</difficult>
		<bndbox>
			<xmin>7349</xmin>
			<ymin>2447</ymin>
			<xmax>7410</xmax>
			<ymax>2534</ymax>
		</bndbox>
	</object>
	<object>
		<name>LAGUA</name>
		<pose>0</pose>
		<truncated>1</truncated>
		<difficult>2</difficult>
		<bndbox>
			<xmin>7958</xmin>
			<ymin>2151</ymin>
			<xmax>8062</xmax>
			<ymax>2208</ymax>
		</bndbox>
	</object>
	<object>
		<name>LAGUA</name>
		<pose>0</pose>
		<truncated>1</truncated>
		<difficult>2</difficult>
		<bndbox>
			<xmin>8063</xmin>
			<ymin>1963</ymin>
			<xmax>8134</xmax>
			<ymax>2040</ymax>
		</bndbox>
	</object>
	<object>
		<name>LAGUA</name>
		<pose>0</pose>
		<truncated>1</truncated>
		<difficult>2</difficult>
		<bndbox>
			<xmin>7686</xmin>
			<ymin>659</ymin>
			<xmax>7735</xmax>
			<ymax>742</ymax>
		</bndbox>
	</object>
</annotation>
